<?xml version="1.0" encoding="UTF-8"?> 

<player xmlns:xsi="http://www.w3.org/2001/XMLSchema-instance" 
    xsi:noNamespaceSchemaLocation="player.xsd"> 
   <team_id>661</team_id> 
   <id>525926</id> 
   <name>إيان ماتسين</name> 
   <image>https://secure.cache.images.core.optasports.com/soccer/players/150x150/525926.png</image> 
   <position>مدافع</position> 
   <nationality>هولندا</nationality> 
   <birth-day>2002-03-10</birth-day> 
   <length  unit="cm">هولندا</length> 
   <weight  unit="kg">167</weight> 
</player>