<?xml version="1.0" encoding="UTF-8"?> 

<player xmlns:xsi="http://www.w3.org/2001/XMLSchema-instance" 
    xsi:noNamespaceSchemaLocation="player.xsd"> 
   <team_id>3490</team_id> 
   <id>539749</id> 
   <name>محمد علي جراد</name> 
   <image>https://secure.cache.images.core.optasports.com/soccer/players/150x150/539749.png</image> 
   <position>حارس مرمى</position> 
   <nationality>تونس</nationality> 
   <birth-day>1997-04-27</birth-day> 
   <length  unit="cm"></length> 
   <weight  unit="kg"></weight> 
</player>