<?xml version="1.0" encoding="UTF-8"?> 

<player xmlns:xsi="http://www.w3.org/2001/XMLSchema-instance" 
    xsi:noNamespaceSchemaLocation="player.xsd"> 
   <team_id>6946</team_id> 
   <id>604984</id> 
   <name>A. Ippolito</name> 
   <image>https://secure.cache.images.core.optasports.com/soccer/players/150x150/604984.png</image> 
   <position>مهاجم</position> 
   <nationality>بلجيكا</nationality> 
   <birth-day>1999-01-05</birth-day> 
   <length  unit="cm"></length> 
   <weight  unit="kg"></weight> 
</player>