<?xml version="1.0" encoding="UTF-8"?> 

<player xmlns:xsi="http://www.w3.org/2001/XMLSchema-instance" 
    xsi:noNamespaceSchemaLocation="player.xsd"> 
   <team_id>3481</team_id> 
   <id>546892</id> 
   <name>T. Lahdhiri</name> 
   <image>https://secure.cache.images.core.optasports.com/soccer/players/150x150/546892.png</image> 
   <position>غير معروف</position> 
   <nationality>تونس</nationality> 
   <birth-day>تونس</birth-day> 
   <length  unit="cm"></length> 
   <weight  unit="kg"></weight> 
</player>