<?xml version="1.0" encoding="UTF-8"?> 

<player xmlns:xsi="http://www.w3.org/2001/XMLSchema-instance" 
    xsi:noNamespaceSchemaLocation="player.xsd"> 
   <team_id>1899</team_id> 
   <id>563564</id> 
   <name>K. Kennedy</name> 
   <image>https://secure.cache.images.core.optasports.com/soccer/players/150x150/563564.png</image> 
   <position>مهاجم</position> 
   <nationality>إسكتلندا</nationality> 
   <birth-day>2002-03-28</birth-day> 
   <length  unit="cm"></length> 
   <weight  unit="kg"></weight> 
</player>