<?xml version="1.0" encoding="UTF-8"?> 

<player xmlns:xsi="http://www.w3.org/2001/XMLSchema-instance" 
    xsi:noNamespaceSchemaLocation="player.xsd"> 
   <team_id>17673</team_id> 
   <id>517719</id> 
   <name>V. Paulauskas</name> 
   <image>https://secure.cache.images.core.optasports.com/soccer/players/150x150/517719.png</image> 
   <position>مدافع</position> 
   <nationality>لتوانيا</nationality> 
   <birth-day>2001-02-04</birth-day> 
   <length  unit="cm"></length> 
   <weight  unit="kg"></weight> 
</player>