<?xml version="1.0" encoding="UTF-8"?> 

<player xmlns:xsi="http://www.w3.org/2001/XMLSchema-instance" 
    xsi:noNamespaceSchemaLocation="player.xsd"> 
   <team_id>1942</team_id> 
   <id>571886</id> 
   <name>M. Pantović</name> 
   <image>https://secure.cache.images.core.optasports.com/soccer/players/150x150/571886.png</image> 
   <position>لاعب وسط</position> 
   <nationality>صربيا</nationality> 
   <birth-day>2002-08-24</birth-day> 
   <length  unit="cm"></length> 
   <weight  unit="kg"></weight> 
</player>