<?xml version="1.0" encoding="UTF-8"?> 

<player xmlns:xsi="http://www.w3.org/2001/XMLSchema-instance" 
    xsi:noNamespaceSchemaLocation="player.xsd"> 
   <team_id>3489</team_id> 
   <id>571561</id> 
   <name> الليفي</name> 
   <image>https://secure.cache.images.core.optasports.com/soccer/players/150x150/571561.png</image> 
   <position>مدافع</position> 
   <nationality>تونس</nationality> 
   <birth-day>1998-05-01</birth-day> 
   <length  unit="cm">اليسرى</length> 
   <weight  unit="kg"></weight> 
</player>