<?xml version="1.0" encoding="UTF-8"?> 

<player xmlns:xsi="http://www.w3.org/2001/XMLSchema-instance" 
    xsi:noNamespaceSchemaLocation="player.xsd"> 
   <team_id>3506</team_id> 
   <id>643753</id> 
   <name>Yousef Baliadeh</name> 
   <image>https://secure.cache.images.core.optasports.com/soccer/players/150x150/643753.png</image> 
   <position>حارس مرمى</position> 
   <nationality>قطر</nationality> 
   <birth-day>2002-10-30</birth-day> 
   <length  unit="cm"></length> 
   <weight  unit="kg"></weight> 
</player>